{"type":"PR","pr":{"number":324,"head":"36f2399f9f24d9c4714e8fccceed710d9e258736"},"user":"George Kokkinidis","status":"draft","branch":"cms/introductions","collection":"components","commitMessage":"Update \"introductions\" page","title":"Introductions","description":"Information about Introductions can be found at:\n\n* <https://cfpb.github.io/design-manual/global-elements/text-introductions.html>\n* <https://cfpb.github.io/design-manual/global-elements/item-introduction.html>\n\nThe text introduction component is the standard page introduction component used across all pages that do not have a [hero](https://cfpb.github.io/design-system/components/heroes) or item introduction.\n\nOn [landing](https://cfpb.github.io/design-system/templates/landing-pages) or [sub-landing pages](https://cfpb.github.io/design-system/templates/sublanding-pages), the text introduction may be accompanied by a breakout sidebar to highlight a specific piece of content from the section.\n\nThe item introduction component is a variation of the text introduction component used on pages found in filterable lists such as blog posts, press releases, or documents.","objects":{"entry":{"path":"docs/components/introductions.md","sha":"c1835d0301f74e014f35899a203df7bcdc881339"},"files":[]},"timeStamp":"2019-09-09T14:32:33.144Z"}