{"type":"PR","pr":{"number":263,"head":"f816cc8aebf2cfa14e1dce45f1b34ad35d580cdb"},"user":"Catherine Farman","status":"draft","branch":"cms/video","collection":"foundation","commitMessage":"Update “video”","title":"Video","description":"Video is a powerful tool that can be used to educate viewers about the financial marketplace and the CFPB’s role in regulating it.\n\nCFPB videos must contain strong emotional and creative imagery while maintaining visual simplicity. Video is a complex medium, so it is essential to pay attention to every detail, for example: composition, color treatment, typography and timing. The audience should recognize a CFPB video through its unique visual treatment.\n\nThis page is under active development. Information is being moved into it from this page:\n\n* http://cfpb.github.io/design-manual/brand-guidelines/video.html","objects":{"entry":{"path":"docs/foundation/video.md","sha":"a7861934d92c5d14be03b753cb7fd553fc8d7e39"},"files":[]},"timeStamp":"2019-08-22T16:23:44.704Z"}